pysmarty2/__init__.py
pysmarty2/connection.py
pysmarty2/exceptions.py
pysmarty2/smarty.py
pysmarty2/registers/__init__.py
pysmarty2/registers/baseregister.py
pysmarty2/registers/coil.py
pysmarty2/registers/coils.json
pysmarty2/registers/discrete_input.py
pysmarty2/registers/discrete_inputs.json
pysmarty2/registers/holding_register.py
pysmarty2/registers/holding_registers.json
pysmarty2/registers/input_register.py
pysmarty2/registers/input_registers.json
pysmarty2/registers/registers.py
pysmarty2-0.10.3.dist-info/licenses/LICENSE
pysmarty2-0.10.3.dist-info/METADATA
pysmarty2-0.10.3.dist-info/WHEEL
pysmarty2-0.10.3.dist-info/top_level.txt
pysmarty2-0.10.3.dist-info/RECORD
