Metadata-Version: 2.4
Name: pysmarty2
Version: 0.10.3
Summary: Python API for Salda Smarty Modbus TCP
Home-page: https://github.com/martinssipenko/pysmarty2
Author: Martins Sipenko, Theo Nicolaum
Author-email: martins.sipenko@gmail.com
Classifier: Programming Language :: Python :: 3
Classifier: License :: OSI Approved :: MIT License
Classifier: Operating System :: OS Independent
License-File: LICENSE
Requires-Dist: pymodbus<4.0.0,>=3.11.0
Dynamic: author
Dynamic: author-email
Dynamic: classifier
Dynamic: description
Dynamic: description-content-type
Dynamic: home-page
Dynamic: license-file
Dynamic: requires-dist
Dynamic: summary
